aiohelpersms/__init__.py
aiohelpersms/aiohelpersms.py
aiohelpersms-0.1.1.dist-info/METADATA
aiohelpersms-0.1.1.dist-info/WHEEL
aiohelpersms-0.1.1.dist-info/top_level.txt
aiohelpersms-0.1.1.dist-info/RECORD
